alas_pkg_core/__init__.py
alas_pkg_core/logger/__init__.py
alas_pkg_core/logger/logger_manager.py
alas_pkg_core/logger/logger_repository.py
alas_pkg_core-0.0.6.dist-info/LICENSE.txt
alas_pkg_core-0.0.6.dist-info/METADATA
alas_pkg_core-0.0.6.dist-info/WHEEL
alas_pkg_core-0.0.6.dist-info/top_level.txt
alas_pkg_core-0.0.6.dist-info/RECORD
