Metadata-Version: 2.1
Name: alas-pkg-core
Version: 0.0.6
Summary: API tools for Alas.Ce0 project
Home-page: https://github.com/pypa/alas-pkg-core
Author: Reynier Blanco Zambrano
Author-email: rblanco@alasxpress.com
License: MIT
Keywords: alas_pkg_core api client development
Platform: UNKNOWN
Classifier: Development Status :: 3 - Alpha
Classifier: Intended Audience :: Developers
Classifier: Topic :: Software Development :: Build Tools
Classifier: License :: OSI Approved :: MIT License
Classifier: Programming Language :: Python :: 3
Requires-Dist: enum34
Requires-Dist: httplib2
Requires-Dist: pendulum
Provides-Extra: dev
Requires-Dist: check-manifest ; extra == 'dev'
Provides-Extra: test
Requires-Dist: coverage ; extra == 'test'
